LICENSE
MANIFEST.in
README.rst
setup.py
diagnose/__init__.py
diagnose/__main__.py
diagnose/cmds.py
diagnose/fileutils.py
diagnose/logs.py
diagnose/queues.py
diagnose/typings.py
diagnose/engine/__init__.py
diagnose/engine/dispatch.py
diagnose/engine/manage.py
diagnose/engine/pipeline.py
diagnose/engine/report.py
diagnose/engine/run.py
diagnose/engine/tracer.py
diagnose/fs/__init__.py
diagnose/fs/base.py
diagnose/fs/models.py
diagnose/plugins/__init__.py
diagnose/plugins/redirect.py
diagnose/plugins/scope.py
diagnose/server/__init__.py
diagnose/server/base.py
diagnose/server/handler.py
diagnose/server/parse.py
diagnose/server/render.py
diagnose/server/templates/control.js
diagnose/server/templates/index.css
diagnose/server/templates/index.html
diagnose/server/ws/__init__.py
diagnose/server/ws/exception.py
diagnose/server/ws/frames.py
diagnose/server/ws/http11.py
diagnose/server/ws/misc.py
diagnose/server/ws/parse.py
diagnose/server/ws/protocol.py
diagnose/server/ws/serve.py
diagnose/server/ws/typings.py
hot_diagnose.egg-info/PKG-INFO
hot_diagnose.egg-info/SOURCES.txt
hot_diagnose.egg-info/dependency_links.txt
hot_diagnose.egg-info/top_level.txt
test/test_script0.py
test/test_script1.py
test/test_script2.py