Metadata-Version: 2.1
Name: hot-diagnose
Version: 0.1rc0
Summary: The runtime code diagnose tool
Home-page: https://github.com/littlebutt/hot-diagnose
Author: littlebutt
Author-email: luogan1996@icloud.com
Requires-Python: >=3.10
License-File: LICENSE
